cli/__init__.py
cli/main.py
cli/commands/__init__.py
cli/commands/accessibility.py
cli/commands/app.py
cli/commands/approve.py
cli/commands/contacts.py
cli/commands/crash.py
cli/commands/daemon.py
cli/commands/dap.py
cli/commands/debugserver.py
cli/commands/dsym.py
cli/commands/dylib.py
cli/commands/file.py
cli/commands/focus.py
cli/commands/framework.py
cli/commands/hid.py
cli/commands/instruments.py
cli/commands/keychain.py
cli/commands/kill.py
cli/commands/launch.py
cli/commands/location.py
cli/commands/log.py
cli/commands/media.py
cli/commands/memory.py
cli/commands/notification.py
cli/commands/revoke.py
cli/commands/screenshot.py
cli/commands/settings.py
cli/commands/shell.py
cli/commands/target.py
cli/commands/url.py
cli/commands/video.py
cli/commands/xctest.py
cli/commands/xctrace.py
cli/tests/__init__.py
cli/tests/connect_tests.py
cli/tests/parser_tests.py
client/__init__.py
common/__init__.py
common/args.py
common/command.py
common/companion.py
common/companion_set.py
common/constants.py
common/file.py
common/format.py
common/gzip.py
common/hid.py
common/logging.py
common/misc.py
common/networking.py
common/plugin.py
common/signal.py
common/socket.py
common/stream.py
common/tar.py
common/types.py
common/udid.py
common/tests/__init__.py
common/tests/companion_set_tests.py
common/tests/companion_tests.py
common/tests/format_tests.py
common/tests/networking_tests.py
common/tests/tar_tests.py
common/tests/udid_tests.py
grpc/__init__.py
grpc/client.py
grpc/crash.py
grpc/dap.py
grpc/file.py
grpc/hid.py
grpc/install.py
grpc/instruments.py
grpc/launch.py
grpc/management.py
grpc/stream.py
grpc/target.py
grpc/video.py
grpc/xctest.py
grpc/xctest_log_parser.py
grpc/xctrace.py
utils/__init__.py
utils/contextlib.py
utils/testing.py
utils/typing.py
idb_answer-0.1.0.dist-info/METADATA
idb_answer-0.1.0.dist-info/WHEEL
idb_answer-0.1.0.dist-info/top_level.txt
idb_answer-0.1.0.dist-info/RECORD
