Metadata-Version: 2.1
Name: idb-answer
Version: 0.1.0
Summary: idb desc
Author: answer.huang
Author-email: answer.huang@nio.com
Keywords: idb-answer
